pip_outdated/__init__.py
pip_outdated/__main__.py
pip_outdated/check_outdated.py
pip_outdated/find_require.py
pip_outdated/print_outdated.py
pip_outdated/session.py
pip_outdated/verbose.py
pip_outdated-0.8.0.dist-info/METADATA
pip_outdated-0.8.0.dist-info/WHEEL
pip_outdated-0.8.0.dist-info/entry_points.txt
pip_outdated-0.8.0.dist-info/top_level.txt
pip_outdated-0.8.0.dist-info/zip-safe
pip_outdated-0.8.0.dist-info/RECORD
