Metadata-Version: 2.4
Name: pip-outdated
Version: 0.8.0
Summary: Find outdated dependencies in your requirements.txt or setup.cfg
Home-page: https://github.com/eight04/pip-outdated
Author: eight
Author-email: eight04@gmail.com
License: MIT
Keywords: pip,check,outdate,npm
Classifier: Development Status :: 4 - Beta
Classifier: Environment :: Console
Classifier: Intended Audience :: Developers
Classifier: Programming Language :: Python :: 3.7
Classifier: Topic :: Software Development :: Build Tools
Requires-Dist: aiohttp~=3.12
Requires-Dist: colorama~=0.4.6
Requires-Dist: packaging~=25.0
Requires-Dist: termcolor~=3.1
Requires-Dist: terminaltables~=3.1
